bot_plugin/__init__.py
bot_plugin/client/__init__.py
bot_plugin/client/app.py
bot_plugin/consts/__init__.py
bot_plugin/consts/routes.py
bot_plugin/domain/__init__.py
bot_plugin/domain/access_type.py
bot_plugin/domain/events.py
bot_plugin/domain/plugin_context.py
bot_plugin/domain/plugin_request.py
bot_plugin/domain/unplug_request.py
bot_plugin/domain/base/__init__.py
bot_plugin/domain/base/serializable.py
bot_plugin/handler/__init__.py
bot_plugin/handler/base/__init__.py
bot_plugin/handler/base/plugin.py
bot_plugin_common-0.0.9.dist-info/METADATA
bot_plugin_common-0.0.9.dist-info/WHEEL
bot_plugin_common-0.0.9.dist-info/licenses/LICENSE
bot_plugin_common-0.0.9.dist-info/RECORD
