Metadata-Version: 2.1
Name: bot_plugin_common
Version: 0.0.9
Summary: This is a fairly simple library for creating a modular Telegram bot architecture.
Project-URL: Homepage, https://github.com/k-panchenko/Bot-plugin-common
Project-URL: Bug Tracker, https://github.com/k-panchenko/Bot-plugin-common/issues
Author-email: Panchenko Konstantin <k.panchenko@simcord.com>
License-File: LICENSE
Classifier: License :: OSI Approved :: MIT License
Classifier: Operating System :: OS Independent
Classifier: Programming Language :: Python :: 3
Requires-Python: >=3.11
